bioio_tiff_glob/__init__.py
bioio_tiff_glob/py.typed
bioio_tiff_glob/reader.py
bioio_tiff_glob/reader_metadata.py
bioio_tiff_glob/utils.py
bioio_tiff_glob/tests/__init__.py
bioio_tiff_glob/tests/test_reader.py
bioio_tiff_glob-1.2.0.dist-info/licenses/LICENSE
bioio_tiff_glob-1.2.0.dist-info/METADATA
bioio_tiff_glob-1.2.0.dist-info/WHEEL
bioio_tiff_glob-1.2.0.dist-info/entry_points.txt
bioio_tiff_glob-1.2.0.dist-info/top_level.txt
bioio_tiff_glob-1.2.0.dist-info/RECORD
